ddlogger/__init__.py
ddlogger/ddlogger.py
ddlogger-0.9b5.dist-info/DESCRIPTION.rst
ddlogger-0.9b5.dist-info/METADATA
ddlogger-0.9b5.dist-info/RECORD
ddlogger-0.9b5.dist-info/WHEEL
ddlogger-0.9b5.dist-info/metadata.json
ddlogger-0.9b5.dist-info/top_level.txt
