Metadata-Version: 2.0
Name: ddlogger
Version: 0.9b5
Summary: Logs progress by printing dots
Home-page: https://github.com/kkew3/dot-dot-logger
Author: Kaiwen Wu
Author-email: kps6326@hotmail.com
License: UNKNOWN
Platform: UNKNOWN
Classifier: Programming Language :: Python
Classifier: License :: OSI Approved :: MIT License
Classifier: Operating System :: OS Independent
Requires-Dist: future
